odoo10_addon_purchase_request_to_rfq_operating_unit-10.0.1.0.0-py2.7-nspkg.pth
odoo/addons/purchase_request_to_rfq_operating_unit/README.rst
odoo/addons/purchase_request_to_rfq_operating_unit/__init__.py
odoo/addons/purchase_request_to_rfq_operating_unit/__manifest__.py
odoo/addons/purchase_request_to_rfq_operating_unit/tests/__init__.py
odoo/addons/purchase_request_to_rfq_operating_unit/tests/test_purchase_request_to_rfq_operating_unit.py
odoo/addons/purchase_request_to_rfq_operating_unit/wizard/__init__.py
odoo/addons/purchase_request_to_rfq_operating_unit/wizard/purchase_request_line_make_purchase_order.py
odoo/addons/purchase_request_to_rfq_operating_unit/wizard/purchase_request_line_make_purchase_order_view.xml
odoo10_addon_purchase_request_to_rfq_operating_unit-10.0.1.0.0.dist-info/DESCRIPTION.rst
odoo10_addon_purchase_request_to_rfq_operating_unit-10.0.1.0.0.dist-info/METADATA
odoo10_addon_purchase_request_to_rfq_operating_unit-10.0.1.0.0.dist-info/RECORD
odoo10_addon_purchase_request_to_rfq_operating_unit-10.0.1.0.0.dist-info/WHEEL
odoo10_addon_purchase_request_to_rfq_operating_unit-10.0.1.0.0.dist-info/metadata.json
odoo10_addon_purchase_request_to_rfq_operating_unit-10.0.1.0.0.dist-info/namespace_packages.txt
odoo10_addon_purchase_request_to_rfq_operating_unit-10.0.1.0.0.dist-info/top_level.txt
