Metadata-Version: 2.0
Name: odoo10-addon-purchase-request-to-rfq-operating-unit
Version: 10.0.1.0.0
Summary: Purchase Request to RFQ with Operating Units
Home-page: http://www.eficent.com
Author: EficentSerpent Consulting Services Pvt. Ltd.,Odoo Community Association (OCA)
Author-email: support@odoo-community.org
License: LGPL-3
Platform: UNKNOWN
Classifier: Programming Language :: Python
Classifier: Framework :: Odoo
Classifier: License :: OSI Approved :: GNU Lesser General Public License v3 (LGPLv3)
Requires-Python: ~=2.7
Requires-Dist: odoo (<10.1dev,>=10.0)
Requires-Dist: odoo10-addon-purchase-request-operating-unit
Requires-Dist: odoo10-addon-purchase-request-to-rfq
